financial_mcp/__init__.py
financial_mcp/analyze.py
financial_mcp/cli.py
financial_mcp/fetch_data.py
financial_mcp/visualize.py
financial_mcp-1.0.0.dist-info/licenses/LICENSE
financial_mcp-1.0.0.dist-info/METADATA
financial_mcp-1.0.0.dist-info/WHEEL
financial_mcp-1.0.0.dist-info/entry_points.txt
financial_mcp-1.0.0.dist-info/top_level.txt
financial_mcp-1.0.0.dist-info/RECORD
