Metadata-Version: 2.4
Name: financial-mcp
Version: 1.0.0
Summary: A comprehensive financial data analysis and visualization package
Author-email: Tatsuru Kikuchi <tatsuru.kikuchi@example.com>
Maintainer-email: Tatsuru Kikuchi <tatsuru.kikuchi@example.com>
License: Apache-2.0
Project-URL: Homepage, https://github.com/Tatsuru-Kikuchi/MCP
Project-URL: Documentation, https://github.com/Tatsuru-Kikuchi/MCP#readme
Project-URL: Repository, https://github.com/Tatsuru-Kikuchi/MCP
Project-URL: Bug Tracker, https://github.com/Tatsuru-Kikuchi/MCP/issues
Project-URL: Live Dashboard, https://tatsuru-kikuchi.github.io/MCP/
Keywords: finance,data-analysis,visualization,stock-market,cryptocurrency,currency,trading,investment,yahoo-finance,financial-modeling
Classifier: Development Status :: 5 - Production/Stable
Classifier: Intended Audience :: Financial and Insurance Industry
Classifier: Intended Audience :: Developers
Classifier: Intended Audience :: Science/Research
Classifier: License :: OSI Approved :: Apache Software License
Classifier: Operating System :: OS Independent
Classifier: Programming Language :: Python :: 3
Classifier: Programming Language :: Python :: 3.8
Classifier: Programming Language :: Python :: 3.9
Classifier: Programming Language :: Python :: 3.10
Classifier: Programming Language :: Python :: 3.11
Classifier: Programming Language :: Python :: 3.12
Classifier: Topic :: Office/Business :: Financial
Classifier: Topic :: Office/Business :: Financial :: Investment
Classifier: Topic :: Scientific/Engineering :: Information Analysis
Classifier: Topic :: Scientific/Engineering :: Visualization
Requires-Python: >=3.8
License-File: LICENSE
Requires-Dist: yfinance>=0.2.28
Requires-Dist: pandas>=2.0.0
Requires-Dist: numpy>=1.24.0
Requires-Dist: matplotlib>=3.5.0
Requires-Dist: seaborn>=0.12.0
Requires-Dist: scipy>=1.10.0
Provides-Extra: dev
Requires-Dist: pytest>=7.0.0; extra == "dev"
Requires-Dist: pytest-cov>=4.0.0; extra == "dev"
Requires-Dist: black>=23.0.0; extra == "dev"
Requires-Dist: flake8>=6.0.0; extra == "dev"
Requires-Dist: mypy>=1.0.0; extra == "dev"
Provides-Extra: jupyter
Requires-Dist: jupyter>=1.0.0; extra == "jupyter"
Requires-Dist: notebook>=6.5.0; extra == "jupyter"
Requires-Dist: ipykernel>=6.0.0; extra == "jupyter"
Provides-Extra: all
Requires-Dist: financial-mcp[dev,jupyter]; extra == "all"
Dynamic: license-file
